{"boards":{"VCU":{"VCU":{"board_id":11,"board_ip":"192.168.1.3","measurements":["VCU_measurements.json"],"packets":["orders.json","packets.json"],"sockets":["sockets.json"]},"VCU_measurements":[{"id":"general_state","name":"General State","type":"uint8"},{"id":"operational_state","name":"Operational State","type":"uint8"},{"id":"recovery_status","name":"Recovery Status","type":"uint8"},{"id":"demonstration_bitfield","name":"Demonstration Bitfield","type":"uint32"},{"id":"flow_1","name":"Flow 1","type":"float32","podUnits":"Hz","displayUnits":"Hz"},{"id":"flow_2","name":"Flow 2","type":"float32","podUnits":"Hz","displayUnits":"Hz"},{"id":"ntc_temperature_1","name":"NTC Temperature 1","type":"float32","podUnits":"ºC","displayUnits":"ºC"},{"id":"ntc_temperature_2","name":"NTC Temperature 2","type":"float32","podUnits":"ºC","displayUnits":"ºC"},{"id":"high_pressure","name":"High Pressure","type":"float32","podUnits":"bar","displayUnits":"bar"},{"id":"low_pressure","name":"Low Pressure","type":"float32","podUnits":"bar","displayUnits":"bar"},{"id":"pressure_regulator_feedback","name":"Pressure Regulator Feedback","type":"float32","podUnits":"bar","displayUnits":"bar"},{"id":"active_brakes","name":"Active Brakes","type":"bool"},{"id":"brake_fault_detected","name":"Brake Fault Detected","type":"bool"},{"id":"cooling_pump_1_command","name":"Cooling Pump 1 Command","type":"uint8","podUnits":"%","displayUnits":"%"},{"id":"cooling_pump_2_command","name":"Cooling Pump 2 Command","type":"uint8","podUnits":"%","displayUnits":"%"},{"id":"electrovalve_enabled","name":"Electrovalve Enabled","type":"bool"},{"id":"sdc_closed","name":"SDC Closed","type":"bool"},{"id":"tapes_reached","name":"Tapes Reached","type":"bool"},{"id":"contactors_closed","name":"Contactors Closed","type":"bool"},{"id":"control_station_connected","name":"Control Station Connected","type":"bool"},{"id":"hvbms_connected","name":"HVBMS Connected","type":"bool"},{"id":"pcu_connected","name":"PCU Connected","type":"bool"},{"id":"lcu_connected","name":"LCU Connected","type":"bool"},{"id":"required_peers_connected","name":"Required Peers Connected","type":"bool"},{"id":"hvbms_state","name":"HVBMS State","type":"uint8"},{"id":"pcu_state","name":"PCU State","type":"uint8"},{"id":"lcu_vertical_state","name":"LCU Vertical State","type":"uint8"},{"id":"lcu_horizontal_state","name":"LCU Horizontal State","type":"uint8"},{"id":"cooling_pump_duty","name":"Cooling Pump Duty","type":"uint8","podUnits":"%","displayUnits":"%"},{"id":"cooling_pump_selection","name":"Cooling Pump Selection","type":"uint8"},{"id":"run_id","name":"Run ID","type":"uint8"},{"id":"modulation_frequency_1","name":"Modulation Frequency 1","type":"float32","podUnits":"Hz","displayUnits":"Hz"},{"id":"commutation_frequency_1","name":"Commutation Frequency 1","type":"float32","podUnits":"Hz","displayUnits":"Hz"},{"id":"reference_voltage_1","name":"Reference Voltage 1","type":"float32","podUnits":"V","displayUnits":"V"},{"id":"max_voltage_1","name":"Max Voltage 1","type":"float32","podUnits":"V","displayUnits":"V"},{"id":"motor_direction_1","name":"Motor Direction 1","type":"uint8"},{"id":"modulation_frequency_2","name":"Modulation Frequency 2","type":"float32","podUnits":"Hz","displayUnits":"Hz"},{"id":"commutation_frequency_2","name":"Commutation Frequency 2","type":"float32","podUnits":"Hz","displayUnits":"Hz"},{"id":"reference_current_2","name":"Reference Current 2","type":"float32","podUnits":"A","displayUnits":"A"},{"id":"max_voltage_2","name":"Max Voltage 2","type":"float32","podUnits":"V","displayUnits":"V"},{"id":"motor_direction_2","name":"Motor Direction 2","type":"uint8"},{"id":"reference_speed_3","name":"Reference Speed 3","type":"float32","podUnits":"m/s","displayUnits":"m/s"},{"id":"commutation_frequency_3","name":"Commutation Frequency 3","type":"float32","podUnits":"Hz","displayUnits":"Hz"},{"id":"max_voltage_3","name":"Max Voltage 3","type":"float32","podUnits":"V","displayUnits":"V"},{"id":"motor_direction_3","name":"Motor Direction 3","type":"uint8"},{"id":"levitation_distance","name":"Levitation Distance","type":"float32","podUnits":"mm","displayUnits":"mm"}],"orders":[{"id":0,"name":"FAULT","type":"order"},{"id":32,"name":"Recovery","type":"order"},{"id":33,"name":"Cooling pump power","type":"order","variables":["cooling_pump_duty","cooling_pump_selection"]},{"id":34,"name":"MANTEINANCE","type":"order"},{"id":35,"name":"Precharge","type":"order"},{"id":36,"name":"Stop","type":"order"},{"id":38,"name":"Propulsion","type":"order"},{"id":39,"name":"Static levitation","type":"order"},{"id":40,"name":"Dynamic levitation","type":"order"},{"id":43,"name":"Brake","type":"order"},{"id":44,"name":"Close contactors","type":"order"},{"id":52,"name":"Unbrake","type":"order"},{"id":53,"name":"Open contactors","type":"order"},{"id":55,"name":"Emergency stop","type":"order"},{"id":56,"name":"Runs","type":"order","variables":["run_id"]},{"id":57,"name":"SVPWM","type":"order","variables":["modulation_frequency_1","commutation_frequency_1","reference_voltage_1","max_voltage_1","motor_direction_1"]},{"id":58,"name":"Stop motor","type":"order"},{"id":59,"name":"Current control","type":"order","variables":["modulation_frequency_2","commutation_frequency_2","reference_current_2","max_voltage_2","motor_direction_2"]},{"id":60,"name":"Speed control","type":"order","variables":["reference_speed_3","commutation_frequency_3","max_voltage_3","motor_direction_3"]},{"id":61,"name":"Motor brake","type":"order"},{"id":37,"name":"Levitation","type":"order","variables":["levitation_distance"]},{"id":46,"name":"Stop levitation","type":"order"},{"id":42,"name":"Booster","type":"order"},{"id":51,"name":"Stop booster","type":"order"},{"id":900,"name":"Remote close contactors","type":"order"},{"id":901,"name":"Remote open contactors","type":"order"},{"id":902,"name":"Remote precharge","type":"order"},{"id":1000,"name":"Remote runs","type":"order","variables":["run_id"]},{"id":1001,"name":"Remote SVPWM","type":"order","variables":["modulation_frequency_1","commutation_frequency_1","reference_voltage_1","max_voltage_1","motor_direction_1"]},{"id":1002,"name":"Remote stop motor","type":"order"},{"id":1003,"name":"Remote current control","type":"order","variables":["modulation_frequency_2","commutation_frequency_2","reference_current_2","max_voltage_2","motor_direction_2"]},{"id":1004,"name":"Remote speed control","type":"order","variables":["reference_speed_3","commutation_frequency_3","max_voltage_3","motor_direction_3"]},{"id":1005,"name":"Remote motor brake","type":"order"},{"id":9989,"name":"Remote levitation","type":"order","variables":["levitation_distance"]},{"id":9993,"name":"Remote stop levitation","type":"order"},{"id":1790,"name":"Remote booster","type":"order"},{"id":1789,"name":"Remote stop booster","type":"order"},{"id":1788,"name":"Forward booster","type":"order"}],"packets":[{"type":"data","name":"VCU State","variables":["general_state","operational_state","recovery_status","demonstration_bitfield"],"id":249,"period_type":"ms","period":100,"socket":"control_station_udp"},{"type":"data","name":"Flow","variables":["flow_1","flow_2"],"id":250,"period_type":"ms","period":16.67,"socket":"control_station_udp"},{"type":"data","name":"Temperatures","variables":["ntc_temperature_1","ntc_temperature_2"],"id":251,"period_type":"ms","period":16.67,"socket":"control_station_udp"},{"type":"data","name":"Pressures","variables":["high_pressure","low_pressure","pressure_regulator_feedback"],"id":252,"period_type":"ms","period":16.67,"socket":"control_station_udp"},{"type":"data","name":"Brake Status","variables":["active_brakes","brake_fault_detected"],"id":253,"period_type":"ms","period":100,"socket":"control_station_udp"},{"type":"data","name":"Outputs","variables":["cooling_pump_1_command","cooling_pump_2_command","electrovalve_enabled"],"id":254,"period_type":"ms","period":100,"socket":"control_station_udp"},{"type":"data","name":"Safety","variables":["sdc_closed","tapes_reached","contactors_closed","control_station_connected","hvbms_connected","pcu_connected","lcu_connected","required_peers_connected"],"id":255,"period_type":"ms","period":100,"socket":"control_station_udp"},{"type":"data","name":"HVBMS State","variables":["hvbms_state"],"id":941},{"type":"data","name":"LCU State","variables":["lcu_vertical_state","lcu_horizontal_state"],"id":63},{"type":"data","name":"PCU State","variables":["pcu_state"],"id":64},{"type":"data","name":"Remote States","variables":["hvbms_state","pcu_state","lcu_vertical_state","lcu_horizontal_state"],"id":65,"period_type":"ms","period":100,"socket":"control_station_udp"},{"type":"data","name":"VCU State For PCU","variables":["recovery_status"],"id":66,"period_type":"ms","period":100,"socket":"pcu_udp"}],"sockets":[{"type":"ServerSocket","name":"control_station_tcp","port":50500},{"type":"DatagramSocket","name":"control_station_udp","remote_ip":"192.168.0.9","port":50400},{"type":"Socket","name":"pcu_tcp","local_port":50501,"remote_ip":"192.168.1.5","remote_port":50500},{"type":"DatagramSocket","name":"pcu_udp","remote_ip":"192.168.1.5","port":50402},{"type":"DatagramSocket","name":"hvbms_udp","remote_ip":"192.168.1.7","port":50403},{"type":"DatagramSocket","name":"lcu_udp","remote_ip":"192.168.1.4","port":50405},{"type":"Socket","name":"hvbms_tcp","local_port":50502,"remote_ip":"192.168.1.7","remote_port":50500},{"type":"Socket","name":"lcu_tcp","local_port":50504,"remote_ip":"192.168.1.4","remote_port":50500}]},"HVBMS-MOCK":{"HVBMS-MOCK":{"board_id":12,"board_ip":"192.168.1.7","measurements":["HVBMS-MOCK_measurements.json"],"packets":["packets.json"],"sockets":["sockets.json"]},"HVBMS-MOCK_measurements":[{"id":"connected_to_master","name":"Connected To Master","type":"bool"}],"packets":[{"type":"data","name":"HVBMS Mock Connection Status","variables":["connected_to_master"],"id":1101,"period_type":"ms","period":100,"socket":"hvbms_mock_control_station_udp"}],"sockets":[{"type":"DatagramSocket","name":"hvbms_mock_control_station_udp","remote_ip":"192.168.0.9","port":50400}]},"LCU-mock":{"LCU-mock":{"board_id":13,"board_ip":"192.168.1.4","measurements":["LCU-mock_measurements.json"],"packets":["packets.json"],"sockets":["sockets.json"]},"LCU-mock_measurements":[{"id":"connected_to_master","name":"Connected To Master","type":"bool"}],"packets":[{"type":"data","name":"LCU Mock Connection Status","variables":["connected_to_master"],"id":1102,"period_type":"ms","period":100,"socket":"lcu_mock_control_station_udp"}],"sockets":[{"type":"DatagramSocket","name":"lcu_mock_control_station_udp","remote_ip":"192.168.0.9","port":50400}]}},"general_info":{"ports":{"TCP_CLIENT":50401,"TCP_SERVER":50500,"UDP":50400,"SNTP":123,"TFTP":69},"addresses":{"backend":"192.168.0.9"},"units":{"m/ss":"*1","Hz":"*1","MOhm":"*1000000","ºC":"+273.15","deg":"/57.2957","km/h":"*3.6","ns":"*1","m/s":"*1","rad":"*1","A":"*1","%":"/100","m":"*1","mrad":"/1000","KOhm":"*1000","V":"*1","mV":"/1000","Ohm":"*1","mm":"/1000","G":"*9.8","bar":"*1","s":"*1"},"message_ids":{"state_space":7,"fault":2,"info":1,"blcu_ack":4,"remove_state_order":6,"add_state_order":5,"warning":3}}}
